folder_structure/__init__.py
folder_structure/folder_structure_generator.py
folder_structure_generator-0.0.2.dist-info/LICENSE
folder_structure_generator-0.0.2.dist-info/METADATA
folder_structure_generator-0.0.2.dist-info/WHEEL
folder_structure_generator-0.0.2.dist-info/top_level.txt
folder_structure_generator-0.0.2.dist-info/RECORD
