Metadata-Version: 2.1
Name: folder-structure-generator
Version: 0.0.2
Summary: The "Folder Structure Generator" simplifies the generation of project directory structures. Easily create a predefined directory tree, copy it to project documentation or README files, and save time when setting up new projects. Eliminate manual directory creation, ensure consistency across projects, and enhance project organization.
Author: Ujjawal Poudel
Author-email: Ujjawal Poudel <ujjawalpoudel@gmail.com>
Project-URL: Repository, https://github.com/ujjawalpoudel/folder-structure-generator
Project-URL: Bug Tracker, https://github.com/ujjawalpoudel/folder-structure-generator/issues
Keywords: python,documentation,structure
Classifier: Programming Language :: Python :: 3
Classifier: License :: OSI Approved :: MIT License
Classifier: Operating System :: OS Independent
Requires-Python: >=3.7
License-File: LICENSE
